PolStringConvertor/PolStringConvertor.py
PolStringConvertor/__init__.py
PolStringConvertor-1.0.0.dist-info/LICENSE.MD
PolStringConvertor-1.0.0.dist-info/METADATA
PolStringConvertor-1.0.0.dist-info/WHEEL
PolStringConvertor-1.0.0.dist-info/top_level.txt
PolStringConvertor-1.0.0.dist-info/RECORD
