Metadata-Version: 2.1
Name: PolStringConvertor
Version: 1.0.0
Summary: A package to convert infix expressions to postfix/prefix and evaluate them
Home-page: https://github.com/CyberPokemon/PolStringConvertor
Author: Imon Mallik
Author-email: imoncoding@gmail.com
Classifier: Programming Language :: Python :: 3
Classifier: License :: OSI Approved :: MIT License
Classifier: Operating System :: OS Independent
Requires-Python: >=3.6
License-File: LICENSE.MD
Requires-Dist: StrTokenizer==1.1.0
